vizlychart/__init__.py
vizlychart/cli.py
vizlychart/demo_comprehensive.py
vizlychart/exceptions.py
vizlychart/figure.py
vizlychart/interaction3d.py
vizlychart/theme.py
vizlychart/vizly_isolation_config.py
vizlychart/ai/__init__.py
vizlychart/ai/nlp.py
vizlychart/ai/smart_selection.py
vizlychart/ai/styling.py
vizlychart/animation/__init__.py
vizlychart/animation/animation_core.py
vizlychart/backends/__init__.py
vizlychart/backends/unified.py
vizlychart/cae/__init__.py
vizlychart/cae/analysis.py
vizlychart/cae/animation.py
vizlychart/cae/fields.py
vizlychart/cae/geometry.py
vizlychart/cae/mesh.py
vizlychart/charts/__init__.py
vizlychart/charts/advanced.py
vizlychart/charts/advanced_charts.py
vizlychart/charts/bar.py
vizlychart/charts/base.py
vizlychart/charts/box.py
vizlychart/charts/chart_3d.py
vizlychart/charts/datascience.py
vizlychart/charts/engineering.py
vizlychart/charts/enhanced_api.py
vizlychart/charts/financial.py
vizlychart/charts/histogram.py
vizlychart/charts/line.py
vizlychart/charts/ml_causal.py
vizlychart/charts/professional_charts.py
vizlychart/charts/scatter.py
vizlychart/charts/surface.py
vizlychart/control/__init__.py
vizlychart/control/axes_control.py
vizlychart/control/layout_control.py
vizlychart/control/styling_control.py
vizlychart/core/__init__.py
vizlychart/core/config.py
vizlychart/core/performance.py
vizlychart/core/renderer.py
vizlychart/core/streaming.py
vizlychart/engineering/__init__.py
vizlychart/engineering/bode.py
vizlychart/engineering/cad_import.py
vizlychart/engineering/cfd.py
vizlychart/engineering/fem.py
vizlychart/engineering/modal.py
vizlychart/engineering/stress.py
vizlychart/engineering/thermal.py
vizlychart/enterprise/__init__.py
vizlychart/enterprise/admin.py
vizlychart/enterprise/api.py
vizlychart/enterprise/benchmarks.py
vizlychart/enterprise/charts.py
vizlychart/enterprise/connectors.py
vizlychart/enterprise/dashboard.py
vizlychart/enterprise/dashboard_server.py
vizlychart/enterprise/docs_server.py
vizlychart-2.4.4.dist-info/licenses/LICENSE
vizlychart-2.4.4.dist-info/METADATA
vizlychart-2.4.4.dist-info/WHEEL
vizlychart-2.4.4.dist-info/entry_points.txt
vizlychart-2.4.4.dist-info/top_level.txt
vizlychart-2.4.4.dist-info/RECORD
