Metadata-Version: 2.4
Name: vizlychart
Version: 2.4.4
Summary: Professional data visualization library with advanced features: 3D plotting, animations, scientific charts, and matplotlib-level control
Home-page: https://github.com/vizly/vizly
Author: Infinidatum Corporation
Author-email: Infinidatum Corporation <durai@infinidatum.net>
Maintainer-email: Infinidatum Corporation <durai@infinidatum.net>
License: MIT
Project-URL: Homepage, https://github.com/vizlychart/vizlychart
Project-URL: Documentation, https://vizlychart.readthedocs.io/
Project-URL: Repository, https://github.com/vizlychart/vizlychart
Project-URL: Bug Tracker, https://github.com/vizlychart/vizlychart/issues
Project-URL: Examples, https://github.com/vizlychart/vizlychart/tree/main/examples
Keywords: visualization,plotting,charts,graphs,data-science,ultra-fast,high-performance,gpu-acceleration,svg-rendering,hdr-colors,professional-typography,precision-rendering,matplotlib-alternative,plotly-alternative,colab-ready,scientific-visualization,engineering-plots,dashboard,real-time-plotting,publication-quality,vizlyengine,cupy,jax,nvidia-gpu,performance-optimization
Classifier: Development Status :: 5 - Production/Stable
Classifier: Intended Audience :: Developers
Classifier: Intended Audience :: Science/Research
Classifier: Intended Audience :: Financial and Insurance Industry
Classifier: Intended Audience :: Education
Classifier: Topic :: Scientific/Engineering :: Visualization
Classifier: Topic :: Scientific/Engineering :: Information Analysis
Classifier: Topic :: Multimedia :: Graphics
Classifier: Topic :: Software Development :: Libraries :: Python Modules
Classifier: License :: OSI Approved :: MIT License
Classifier: Programming Language :: Python :: 3
Classifier: Programming Language :: Python :: 3.7
Classifier: Programming Language :: Python :: 3.8
Classifier: Programming Language :: Python :: 3.9
Classifier: Programming Language :: Python :: 3.10
Classifier: Programming Language :: Python :: 3.11
Classifier: Programming Language :: Python :: 3.12
Classifier: Operating System :: OS Independent
Classifier: Environment :: Console
Classifier: Environment :: Web Environment
Requires-Python: >=3.7
License-File: LICENSE
Requires-Dist: numpy>=1.24.0
Requires-Dist: matplotlib>=3.7.0; extra == "extended"
Requires-Dist: scipy>=1.11.0; extra == "extended"
Provides-Extra: extended
Requires-Dist: matplotlib>=3.7.0; extra == "extended"
Requires-Dist: scipy>=1.11.0; extra == "extended"
Provides-Extra: gpu
Requires-Dist: cupy-cuda11x>=12.0.0; extra == "gpu"
Requires-Dist: jax>=0.4.0; extra == "gpu"
Requires-Dist: jaxlib>=0.4.0; extra == "gpu"
Provides-Extra: dev
Requires-Dist: pytest>=7.0.0; extra == "dev"
Requires-Dist: pytest-cov>=4.0.0; extra == "dev"
Requires-Dist: black>=23.0.0; extra == "dev"
Requires-Dist: ruff>=0.1.0; extra == "dev"
Requires-Dist: mypy>=1.0.0; extra == "dev"
Requires-Dist: twine>=4.0.0; extra == "dev"
Requires-Dist: build>=0.10.0; extra == "dev"
Provides-Extra: all
Requires-Dist: matplotlib>=3.7.0; extra == "all"
Requires-Dist: scipy>=1.11.0; extra == "all"
Requires-Dist: cupy-cuda11x>=12.0.0; extra == "all"
Requires-Dist: jax>=0.4.0; extra == "all"
Requires-Dist: jaxlib>=0.4.0; extra == "all"
Dynamic: author
Dynamic: home-page
Dynamic: license-file
Dynamic: requires-python
